odoo/addons/l10n_br_fiscal_notification/README.rst
odoo/addons/l10n_br_fiscal_notification/__init__.py
odoo/addons/l10n_br_fiscal_notification/__manifest__.py
odoo/addons/l10n_br_fiscal_notification/data/l10n_br_fiscal_email_template.xml
odoo/addons/l10n_br_fiscal_notification/demo/l10n_br_fiscal_document_email.xml
odoo/addons/l10n_br_fiscal_notification/demo/l10n_br_fiscal_document_email.xml.orig
odoo/addons/l10n_br_fiscal_notification/i18n/l10n_br_fiscal_notification.pot
odoo/addons/l10n_br_fiscal_notification/models/__init__.py
odoo/addons/l10n_br_fiscal_notification/models/document.py
odoo/addons/l10n_br_fiscal_notification/models/document_email.py
odoo/addons/l10n_br_fiscal_notification/models/document_type.py
odoo/addons/l10n_br_fiscal_notification/models/res_company.py
odoo/addons/l10n_br_fiscal_notification/readme/CONTRIBUTORS.md
odoo/addons/l10n_br_fiscal_notification/readme/DESCRIPTION.md
odoo/addons/l10n_br_fiscal_notification/security/fiscal_security.xml
odoo/addons/l10n_br_fiscal_notification/security/ir.model.access.csv
odoo/addons/l10n_br_fiscal_notification/static/description/icon.png
odoo/addons/l10n_br_fiscal_notification/static/description/index.html
odoo/addons/l10n_br_fiscal_notification/views/document_email_view.xml
odoo/addons/l10n_br_fiscal_notification/views/document_type_view.xml
odoo/addons/l10n_br_fiscal_notification/views/document_view.xml
odoo/addons/l10n_br_fiscal_notification/views/l10n_br_fiscal_action.xml
odoo/addons/l10n_br_fiscal_notification/views/l10n_br_fiscal_menu.xml
odoo_addon_l10n_br_fiscal_notification-16.0.1.1.0.dist-info/METADATA
odoo_addon_l10n_br_fiscal_notification-16.0.1.1.0.dist-info/WHEEL
odoo_addon_l10n_br_fiscal_notification-16.0.1.1.0.dist-info/top_level.txt
odoo_addon_l10n_br_fiscal_notification-16.0.1.1.0.dist-info/RECORD
